LICENSE
README.md
setup.py
WTTI.egg-info/PKG-INFO
WTTI.egg-info/SOURCES.txt
WTTI.egg-info/dependency_links.txt
WTTI.egg-info/requires.txt
WTTI.egg-info/top_level.txt
test/test_Content.py
test/test_Post.py
test/test_Proxy.py
test/test_Text.py
test/test_output.py
test/test_utils.py
wtti/Comment.py
wtti/Content.py
wtti/Post.py
wtti/Proxy.py
wtti/Text.py
wtti/__init__.py
wtti/output.py
wtti/utils.py
wtti/version_check.py