Metadata-Version: 2.1
Name: WTTI
Version: 0.3.0
Summary: Webpage Text Transformation Interface，將網頁文章內容以結構化方式儲存，以方便後續分析應用。
Home-page: https://github.com/Keycatowo/WTTI
Author: owo
Author-email: contact@owomail.cc
License: UNKNOWN
Platform: UNKNOWN
Classifier: Programming Language :: Python :: 3
Classifier: License :: OSI Approved :: MIT License
Classifier: Operating System :: OS Independent
License-File: LICENSE
